opendota/__init__.py
opendota/client.py
opendota/constants.py
opendota/exceptions.py
opendota/fantasy.py
opendota/endpoints/__init__.py
opendota/endpoints/base.py
opendota/models/__init__.py
opendota/models/hero.py
opendota/models/league.py
opendota/models/match.py
opendota/models/parse_job.py
opendota/models/player.py
opendota/models/pro_player.py
opendota/models/team.py
python_opendota_sdk-7.40.3.dist-info/METADATA
python_opendota_sdk-7.40.3.dist-info/WHEEL
python_opendota_sdk-7.40.3.dist-info/licenses/LICENSE
python_opendota_sdk-7.40.3.dist-info/RECORD
