Metadata-Version: 2.4
Name: python-opendota-sdk
Version: 7.40.3
Summary: Modern async Python wrapper for the OpenDota API with full type support
Project-URL: Homepage, https://github.com/DeepBlueCoding/python-opendota-sdk
Project-URL: Documentation, https://deepbluecoding.github.io/python-opendota-sdk/
Project-URL: Repository, https://github.com/DeepBlueCoding/python-opendota-sdk
Project-URL: Bug Tracker, https://github.com/DeepBlueCoding/python-opendota-sdk/issues
Project-URL: Changelog, https://github.com/DeepBlueCoding/python-opendota-sdk/blob/master/CHANGELOG.md
Author: Python OpenDota Contributors
Maintainer: Python OpenDota Contributors
License-Expression: MIT
License-File: LICENSE
Keywords: api,async,client,dota2,esports,gaming,opendota,wrapper
Classifier: Development Status :: 4 - Beta
Classifier: Intended Audience :: Developers
Classifier: License :: OSI Approved :: MIT License
Classifier: Operating System :: OS Independent
Classifier: Programming Language :: Python :: 3
Classifier: Programming Language :: Python :: 3.9
Classifier: Programming Language :: Python :: 3.10
Classifier: Programming Language :: Python :: 3.11
Classifier: Programming Language :: Python :: 3.12
Classifier: Programming Language :: Python :: 3.13
Classifier: Topic :: Games/Entertainment
Classifier: Topic :: Internet :: WWW/HTTP :: Dynamic Content
Classifier: Topic :: Software Development :: Libraries :: Python Modules
Classifier: Typing :: Typed
Requires-Python: >=3.9
Requires-Dist: httpx>=0.25.0
Requires-Dist: pydantic>=2.0.0
Requires-Dist: typing-extensions>=4.0.0; python_version < '3.10'
Provides-Extra: dev
Requires-Dist: build>=1.0.0; extra == 'dev'
Requires-Dist: pytest-asyncio>=0.21.0; extra == 'dev'
Requires-Dist: pytest-httpx>=0.21.0; extra == 'dev'
Requires-Dist: pytest>=7.0.0; extra == 'dev'
Requires-Dist: python-dotenv>=1.0.0; extra == 'dev'
Requires-Dist: twine>=5.0.0; extra == 'dev'
Requires-Dist: wheel>=0.42.0; extra == 'dev'
